{
  "raven": {
    "provider": "raven",
    "module": "passport-raven",
    "desc": "Churchill College Spring Ball",
    "msg": "We need to check you are a college member",
    "debug": false,
    "passReqToCallback": true,

    "audience": "http://localhost:3001 || http://131.111.202.70:8000",

    "authScheme": "openid",
    "authPath": "/auth/raven",
    "callbackURL": "/auth/raven",
    "callbackPath": "/auth/raven",
    "successRedirect": "/auth/success",
    "failureRedirect": "/login",
    "scope": ["email"],
    "failureFlash": true
  }
}
